{"modules":[{"id":"2854bbfd-7750-450e-9684-f73aebe76110","type":"Disconnect","branches":[],"parameters":[],"metadata":{"position":{"x":815,"y":384}}},{"id":"27adc42b-4a47-4e50-8673-32236ec80f16","type":"SetQueue","branches":[{"condition":"Success","transition":"efff0ad4-012a-4913-b33a-5e6b32efe192"},{"condition":"Error","transition":"2854bbfd-7750-450e-9684-f73aebe76110"}],"parameters":[{"name":"Queue","value":"arn:aws:connect:us-east-1:734805743552:instance/717ab265-dd50-476b-976c-0ce5fac38807/queue/250e895f-679e-473a-8032-560549091807","namespace":null,"resourceName":"Tech_support"}],"metadata":{"position":{"x":296,"y":283},"useDynamic":false,"queue":{"id":"arn:aws:connect:us-east-1:734805743552:instance/717ab265-dd50-476b-976c-0ce5fac38807/queue/250e895f-679e-473a-8032-560549091807","text":"Tech_support"}}},{"id":"efff0ad4-012a-4913-b33a-5e6b32efe192","type":"Transfer","branches":[{"condition":"AtCapacity","transition":"2854bbfd-7750-450e-9684-f73aebe76110"},{"condition":"Error","transition":"2854bbfd-7750-450e-9684-f73aebe76110"}],"parameters":[],"metadata":{"position":{"x":546,"y":250},"useDynamic":false,"queue":null},"target":"Queue"},{"id":"e06e5db3-91f0-4892-961f-f5901c0bbbc2","type":"SetRecordingBehavior","branches":[{"condition":"Success","transition":"2fd6416a-4cfe-4df0-bbb1-53cbe4b79bcf"}],"parameters":[{"name":"RecordingBehaviorOption","value":"Enable"},{"name":"RecordingParticipantOption","value":"Both"},{"name":"AnalyticsBehaviorOption","value":"Enable"},{"name":"AnalyticsLanguageLocaleCode","value":"en-US","namespace":null},{"name":"AnalyticsCustomVocabulary","value":"None"},{"name":"AnalyticsRedactionOption","value":"Disable"},{"name":"AnalyticsRedactionPolicy","value":"None","namespace":null},{"name":"AnalyticsMode","value":"RealTime"}],"metadata":{"position":{"x":172,"y":28}}},{"id":"6af13111-4bee-43b7-8ac3-7cceee02b424","type":"SetEventHook","branches":[{"condition":"Success","transition":"27adc42b-4a47-4e50-8673-32236ec80f16"},{"condition":"Error","transition":"27adc42b-4a47-4e50-8673-32236ec80f16"}],"parameters":[{"name":"Type","value":"CustomerRemaining"},{"name":"ContactFlowId","value":"arn:aws:connect:us-east-1:734805743552:instance/717ab265-dd50-476b-976c-0ce5fac38807/contact-flow/f335cb03-a3e9-47ac-a8ec-a3e1ec58f420","resourceName":"Post Call Survey"}],"metadata":{"position":{"x":45,"y":268},"contactFlow":{"id":"arn:aws:connect:us-east-1:734805743552:instance/717ab265-dd50-476b-976c-0ce5fac38807/contact-flow/f335cb03-a3e9-47ac-a8ec-a3e1ec58f420","text":"Post Call Survey"},"useDynamic":false}},{"id":"62bcdc40-cbb8-4b13-8f7f-fa093de4d0d6","type":"PlayPrompt","branches":[{"condition":"Success","transition":"6af13111-4bee-43b7-8ac3-7cceee02b424"}],"parameters":[{"name":"Text","value":"Hi. Please wait for an agent to answer.","namespace":null},{"name":"TextToSpeechType","value":"text"}],"metadata":{"position":{"x":881,"y":33},"useDynamic":false}},{"id":"2fd6416a-4cfe-4df0-bbb1-53cbe4b79bcf","type":"SetLoggingBehavior","branches":[{"condition":"Success","transition":"5cbd8cc8-d38c-48f4-8fbe-25202706302f"}],"parameters":[{"name":"LoggingBehavior","value":"Enable"}],"metadata":{"position":{"x":396,"y":29}}},{"id":"5cbd8cc8-d38c-48f4-8fbe-25202706302f","type":"CreateTask","branches":[{"condition":"Success","transition":"62bcdc40-cbb8-4b13-8f7f-fa093de4d0d6"},{"condition":"Error","transition":"62bcdc40-cbb8-4b13-8f7f-fa093de4d0d6"}],"parameters":[{"name":"ContactFlowId","value":"arn:aws:connect:us-east-1:734805743552:instance/717ab265-dd50-476b-976c-0ce5fac38807/contact-flow/2af23998-70e3-46df-bb78-b3817edbcc84","resourceName":"TaskFlow"},{"name":"ContactData","contactName":"TEST_FROM_IVR","namespace":null},{"name":"ContactData","contactDescription":"Test task sent from IVR","namespace":null},{"name":"ContactData","namespace":null,"contactReference":{"key":"url1","value":"https://www.youtube.com/watch?v=dQw4w9W","type":"URL"}},{"name":"ContactData","namespace":null,"contactReference":{"key":"url2","value":"https://www.google.com","type":"URL"}},{"name":"Attribute","value":"test_value","key":"test_key","namespace":null}],"metadata":{"position":{"x":637,"y":15},"useDynamicContactFlow":false,"useDynamicDelay":false,"delayUnit":{"display":"Seconds","value":"second"},"ContactFlow":{"id":"arn:aws:connect:us-east-1:734805743552:instance/717ab265-dd50-476b-976c-0ce5fac38807/contact-flow/2af23998-70e3-46df-bb78-b3817edbcc84","text":"TaskFlow","arn":null,"metricDetail":null,"resourceId":null}}}],"version":"1","start":"e06e5db3-91f0-4892-961f-f5901c0bbbc2","metadata":{"entryPointPosition":{"x":20,"y":61},"snapToGrid":false,"name":"MainFlow","description":null,"type":"contactFlow","status":"published","hash":"ab5af1fb532ca52f4754c1b58ba078c2a26b8f3d788185af2154b6f672cd6f81"},"type":"contactFlow"}